{
  "site_id": "reference-2",
  "site_name": "Reference-2",
  "category": "reference",
  "architecture": "server-rendered, legacy",
  "status": "success",
  "har_files_analyzed": 12,
  "summary": {
    "avg_total_requests": 166.5,
    "avg_api_requests": 11.3,
    "avg_total_bytes_kb": 1202.5,
    "quality_score": 84.3
  },
  "dimension_scores": {
    "redundant_calls": 85.0,
    "n_plus_1": 100.0,
    "sequential_waterfalls": 24.1,
    "missing_cache_headers": 75.8,
    "oversized_payloads": 92.5,
    "missing_compression": 89.3,
    "third_party_overhead": 100.0,
    "error_rate": 100.0
  },
  "anti_pattern_averages": {
    "redundant_excess_calls": 1.5,
    "n_plus_1_patterns": 0.0,
    "missing_cache_pct": 24.2,
    "oversized_payloads": 0.5,
    "uncompressed_responses": 1.2,
    "third_party_pct": 0.0,
    "error_rate_pct": 0.0
  },
  "analyzed_at": "2026-02-08T00:23:37.160620",
  "captures_analyzed": 12
}